bctools/__init__.py
bctools/main.py
bctools/modules/__init__.py
bctools/modules/auto.py
bctools/modules/cluster.py
bctools/modules/correct.py
bctools/modules/detect.py
bctools/static/env.yaml
bctools/utils/__init__.py
bctools-0.0.1.dist-info/METADATA
bctools-0.0.1.dist-info/WHEEL
bctools-0.0.1.dist-info/entry_points.txt
bctools-0.0.1.dist-info/RECORD
