Metadata-Version: 2.3
Name: bctools
Version: 0.0.1
Summary: 
Author: DeYing Zhang
Author-email: legendzdy@dingtalk.com
Requires-Python: >=3.10
Classifier: Programming Language :: Python :: 3
Classifier: Programming Language :: Python :: 3.10
Classifier: Programming Language :: Python :: 3.11
Classifier: Programming Language :: Python :: 3.12
Classifier: Programming Language :: Python :: 3.13
Requires-Dist: basebio (>=0.4.8)
Requires-Dist: typer (>=0.15.2)
